logging_forensic/__init__.py
logging_forensic/core.py
logging_forensic-0.1.1.dist-info/METADATA
logging_forensic-0.1.1.dist-info/WHEEL
logging_forensic-0.1.1.dist-info/top_level.txt
logging_forensic-0.1.1.dist-info/RECORD
