Metadata-Version: 2.4
Name: logging-forensic
Version: 0.1.1
Summary: Forensic logging setup for python projects
Author: Dietmar Fackelmann
Author-email: Dietmar Fackelmann <fackelm2@nmit.de>
License-Expression: MIT
Project-URL: Homepage, https://github.com/fackelm2/logging-forensic
Requires-Python: >=3.12
Dynamic: author
